vy4e_optmodel/__init__.py
vy4e_optmodel/__main__.py
vy4e_optmodel/oM_Main.py
vy4e_optmodel/Home1/oM_Data_Duration_Home1.csv
vy4e_optmodel/Home1/oM_Data_ElectricityDemand_Home1.csv
vy4e_optmodel/Home1/oM_Data_ElectricityGeneration_Home1.csv
vy4e_optmodel/Home1/oM_Data_ElectricityNetwork_Home1.csv
vy4e_optmodel/Home1/oM_Data_ElectricityRetail_Home1.csv
vy4e_optmodel/Home1/oM_Data_HydrogenDemand_Home1.csv
vy4e_optmodel/Home1/oM_Data_HydrogenGeneration_Home1.csv
vy4e_optmodel/Home1/oM_Data_HydrogenNetwork_Home1.csv
vy4e_optmodel/Home1/oM_Data_HydrogenRetail_Home1.csv
vy4e_optmodel/Home1/oM_Data_NodeLocation_Home1.csv
vy4e_optmodel/Home1/oM_Data_OperatingReserveActivation_Home1.csv
vy4e_optmodel/Home1/oM_Data_OperatingReservePrice_Home1.csv
vy4e_optmodel/Home1/oM_Data_OperatingReserveRequire_Home1.csv
vy4e_optmodel/Home1/oM_Data_Option_Home1.csv
vy4e_optmodel/Home1/oM_Data_Parameter_Home1.csv
vy4e_optmodel/Home1/oM_Data_Period_Home1.csv
vy4e_optmodel/Home1/oM_Data_Scenario_Home1.csv
vy4e_optmodel/Home1/oM_Data_Tariff_Home1.csv
vy4e_optmodel/Home1/oM_Data_VarEnergyCost_Home1.csv
vy4e_optmodel/Home1/oM_Data_VarEnergyPrice_Home1.csv
vy4e_optmodel/Home1/oM_Data_VarMaxConsumption_Home1.csv
vy4e_optmodel/Home1/oM_Data_VarMaxDemand_Home1.csv
vy4e_optmodel/Home1/oM_Data_VarMaxEmissionCost_Home1.csv
vy4e_optmodel/Home1/oM_Data_VarMaxEnergy_Home1.csv
vy4e_optmodel/Home1/oM_Data_VarMaxFuelCost_Home1.csv
vy4e_optmodel/Home1/oM_Data_VarMaxGeneration_Home1.csv
vy4e_optmodel/Home1/oM_Data_VarMaxInflows_Home1.csv
vy4e_optmodel/Home1/oM_Data_VarMaxOutflows_Home1.csv
vy4e_optmodel/Home1/oM_Data_VarMaxStorage_Home1.csv
vy4e_optmodel/Home1/oM_Data_VarMinConsumption_Home1.csv
vy4e_optmodel/Home1/oM_Data_VarMinDemand_Home1.csv
vy4e_optmodel/Home1/oM_Data_VarMinEmissionCost_Home1.csv
vy4e_optmodel/Home1/oM_Data_VarMinEnergy_Home1.csv
vy4e_optmodel/Home1/oM_Data_VarMinFuelCost_Home1.csv
vy4e_optmodel/Home1/oM_Data_VarMinGeneration_Home1.csv
vy4e_optmodel/Home1/oM_Data_VarMinInflows_Home1.csv
vy4e_optmodel-1.0.15.dist-info/entry_points.txt
vy4e_optmodel-1.0.15.dist-info/licenses/LICENSE
vy4e_optmodel-1.0.15.dist-info/WHEEL
vy4e_optmodel-1.0.15.dist-info/METADATA
vy4e_optmodel-1.0.15.dist-info/RECORD
